<?xml version="1.0" encoding="UTF-8"?>
<!DOCTYPE mapper PUBLIC "-//mybatis.org//DTD Mapper 3.0//EN" "http://mybatis.org/dtd/mybatis-3-mapper.dtd">
<mapper namespace="edu.tyut.dao.ElectiveScoreMapper">
  <resultMap id="BaseResultMap" type="edu.tyut.bean.mbg.ElectiveScore">
    <!--
      WARNING - @mbg.generated
      This element is automatically generated by MyBatis Generator, do not modify.
      This element was generated on Fri Jun 05 21:19:30 CST 2020.
    -->
    <result column="student_id" jdbcType="VARCHAR" property="studentId" />
    <result column="student_name" jdbcType="VARCHAR" property="studentName" />
    <result column="elective_id" jdbcType="INTEGER" property="electiveId" />
    <result column="elective_name" jdbcType="VARCHAR" property="electiveName" />
    <result column="score" jdbcType="INTEGER" property="score" />
  </resultMap>
  <sql id="Example_Where_Clause">
    <!--
      WARNING - @mbg.generated
      This element is automatically generated by MyBatis Generator, do not modify.
      This element was generated on Fri Jun 05 21:19:30 CST 2020.
    -->
    <where>
      <foreach collection="oredCriteria" item="criteria" separator="or">
        <if test="criteria.valid">
          <trim prefix="(" prefixOverrides="and" suffix=")">
            <foreach collection="criteria.criteria" item="criterion">
              <choose>
                <when test="criterion.noValue">
                  and ${criterion.condition}
                </when>
                <when test="criterion.singleValue">
                  and ${criterion.condition} #{criterion.value}
                </when>
                <when test="criterion.betweenValue">
                  and ${criterion.condition} #{criterion.value} and #{criterion.secondValue}
                </when>
                <when test="criterion.listValue">
                  and ${criterion.condition}
                  <foreach close=")" collection="criterion.value" item="listItem" open="(" separator=",">
                    #{listItem}
                  </foreach>
                </when>
              </choose>
            </foreach>
          </trim>
        </if>
      </foreach>
    </where>
  </sql>
  <sql id="Update_By_Example_Where_Clause">
    <!--
      WARNING - @mbg.generated
      This element is automatically generated by MyBatis Generator, do not modify.
      This element was generated on Fri Jun 05 21:19:30 CST 2020.
    -->
    <where>
      <foreach collection="example.oredCriteria" item="criteria" separator="or">
        <if test="criteria.valid">
          <trim prefix="(" prefixOverrides="and" suffix=")">
            <foreach collection="criteria.criteria" item="criterion">
              <choose>
                <when test="criterion.noValue">
                  and ${criterion.condition}
                </when>
                <when test="criterion.singleValue">
                  and ${criterion.condition} #{criterion.value}
                </when>
                <when test="criterion.betweenValue">
                  and ${criterion.condition} #{criterion.value} and #{criterion.secondValue}
                </when>
                <when test="criterion.listValue">
                  and ${criterion.condition}
                  <foreach close=")" collection="criterion.value" item="listItem" open="(" separator=",">
                    #{listItem}
                  </foreach>
                </when>
              </choose>
            </foreach>
          </trim>
        </if>
      </foreach>
    </where>
  </sql>
  <sql id="Base_Column_List">
    <!--
      WARNING - @mbg.generated
      This element is automatically generated by MyBatis Generator, do not modify.
      This element was generated on Fri Jun 05 21:19:30 CST 2020.
    -->
    student_id, student_name, elective_id, elective_name, score
  </sql>
  <select id="selectByExample" parameterType="edu.tyut.bean.example.ElectiveScoreExample" resultMap="BaseResultMap">
    <!--
      WARNING - @mbg.generated
      This element is automatically generated by MyBatis Generator, do not modify.
      This element was generated on Fri Jun 05 21:19:30 CST 2020.
    -->
    select
    <if test="distinct">
      distinct
    </if>
    <include refid="Base_Column_List" />
    from elective_score
    <if test="_parameter != null">
      <include refid="Example_Where_Clause" />
    </if>
    <if test="orderByClause != null">
      order by ${orderByClause}
    </if>
  </select>
  <delete id="deleteByExample" parameterType="edu.tyut.bean.example.ElectiveScoreExample">
    <!--
      WARNING - @mbg.generated
      This element is automatically generated by MyBatis Generator, do not modify.
      This element was generated on Fri Jun 05 21:19:30 CST 2020.
    -->
    delete from elective_score
    <if test="_parameter != null">
      <include refid="Example_Where_Clause" />
    </if>
  </delete>
  <insert id="insert" parameterType="edu.tyut.bean.mbg.ElectiveScore">
    <!--
      WARNING - @mbg.generated
      This element is automatically generated by MyBatis Generator, do not modify.
      This element was generated on Fri Jun 05 21:19:30 CST 2020.
    -->
    insert into elective_score (student_id, student_name, elective_id, 
      elective_name, score)
    values (#{studentId,jdbcType=VARCHAR}, #{studentName,jdbcType=VARCHAR}, #{electiveId,jdbcType=INTEGER}, 
      #{electiveName,jdbcType=VARCHAR}, #{score,jdbcType=INTEGER})
  </insert>
  <insert id="insertSelective" parameterType="edu.tyut.bean.mbg.ElectiveScore">
    <!--
      WARNING - @mbg.generated
      This element is automatically generated by MyBatis Generator, do not modify.
      This element was generated on Fri Jun 05 21:19:30 CST 2020.
    -->
    insert into elective_score
    <trim prefix="(" suffix=")" suffixOverrides=",">
      <if test="studentId != null">
        student_id,
      </if>
      <if test="studentName != null">
        student_name,
      </if>
      <if test="electiveId != null">
        elective_id,
      </if>
      <if test="electiveName != null">
        elective_name,
      </if>
      <if test="score != null">
        score,
      </if>
    </trim>
    <trim prefix="values (" suffix=")" suffixOverrides=",">
      <if test="studentId != null">
        #{studentId,jdbcType=VARCHAR},
      </if>
      <if test="studentName != null">
        #{studentName,jdbcType=VARCHAR},
      </if>
      <if test="electiveId != null">
        #{electiveId,jdbcType=INTEGER},
      </if>
      <if test="electiveName != null">
        #{electiveName,jdbcType=VARCHAR},
      </if>
      <if test="score != null">
        #{score,jdbcType=INTEGER},
      </if>
    </trim>
  </insert>
  <select id="countByExample" parameterType="edu.tyut.bean.example.ElectiveScoreExample" resultType="java.lang.Long">
    <!--
      WARNING - @mbg.generated
      This element is automatically generated by MyBatis Generator, do not modify.
      This element was generated on Fri Jun 05 21:19:30 CST 2020.
    -->
    select count(*) from elective_score
    <if test="_parameter != null">
      <include refid="Example_Where_Clause" />
    </if>
  </select>
  <update id="updateByExampleSelective" parameterType="map">
    <!--
      WARNING - @mbg.generated
      This element is automatically generated by MyBatis Generator, do not modify.
      This element was generated on Fri Jun 05 21:19:30 CST 2020.
    -->
    update elective_score
    <set>
      <if test="record.studentId != null">
        student_id = #{record.studentId,jdbcType=VARCHAR},
      </if>
      <if test="record.studentName != null">
        student_name = #{record.studentName,jdbcType=VARCHAR},
      </if>
      <if test="record.electiveId != null">
        elective_id = #{record.electiveId,jdbcType=INTEGER},
      </if>
      <if test="record.electiveName != null">
        elective_name = #{record.electiveName,jdbcType=VARCHAR},
      </if>
      <if test="record.score != null">
        score = #{record.score,jdbcType=INTEGER},
      </if>
    </set>
    <if test="_parameter != null">
      <include refid="Update_By_Example_Where_Clause" />
    </if>
  </update>
  <update id="updateByExample" parameterType="map">
    <!--
      WARNING - @mbg.generated
      This element is automatically generated by MyBatis Generator, do not modify.
      This element was generated on Fri Jun 05 21:19:30 CST 2020.
    -->
    update elective_score
    set student_id = #{record.studentId,jdbcType=VARCHAR},
      student_name = #{record.studentName,jdbcType=VARCHAR},
      elective_id = #{record.electiveId,jdbcType=INTEGER},
      elective_name = #{record.electiveName,jdbcType=VARCHAR},
      score = #{record.score,jdbcType=INTEGER}
    <if test="_parameter != null">
      <include refid="Update_By_Example_Where_Clause" />
    </if>
  </update>
</mapper>